metaclass_registry/__init__.py
metaclass_registry/_home.py
metaclass_registry/cache.py
metaclass_registry/core.py
metaclass_registry/discovery.py
metaclass_registry/exceptions.py
metaclass_registry-0.1.4.dist-info/METADATA
metaclass_registry-0.1.4.dist-info/WHEEL
metaclass_registry-0.1.4.dist-info/licenses/LICENSE
metaclass_registry-0.1.4.dist-info/RECORD
