Metadata-Version: 2.4
Name: metaclass-registry
Version: 0.1.4
Summary: Zero-boilerplate metaclass-driven plugin registry system with lazy discovery and caching
Project-URL: Homepage, https://github.com/OpenHCSDev/metaclass-registry
Project-URL: Documentation, https://metaclass-registry.readthedocs.io
Project-URL: Repository, https://github.com/OpenHCSDev/metaclass-registry
Project-URL: Issues, https://github.com/OpenHCSDev/metaclass-registry/issues
Author-email: Tristan Simas <tristan.simas@mail.mcgill.ca>
License: MIT
License-File: LICENSE
Keywords: cache,discovery,lazy-loading,metaclass,plugin,registry
Classifier: Development Status :: 4 - Beta
Classifier: Intended Audience :: Developers
Classifier: License :: OSI Approved :: MIT License
Classifier: Programming Language :: Python :: 3
Classifier: Programming Language :: Python :: 3.9
Classifier: Programming Language :: Python :: 3.10
Classifier: Programming Language :: Python :: 3.11
Classifier: Programming Language :: Python :: 3.12
Classifier: Topic :: Software Development :: Libraries :: Python Modules
Classifier: Topic :: Utilities
Requires-Python: >=3.9
Provides-Extra: dev
Requires-Dist: black>=23.0; extra == 'dev'
Requires-Dist: mypy>=1.0; extra == 'dev'
Requires-Dist: pytest-cov>=4.0; extra == 'dev'
Requires-Dist: pytest>=7.0; extra == 'dev'
Requires-Dist: ruff>=0.1.0; extra == 'dev'
Provides-Extra: docs
Requires-Dist: sphinx-rtd-theme>=2.0; extra == 'docs'
Requires-Dist: sphinx>=7.0; extra == 'docs'
